sudeep/__init__.py
sudeep-0.1.0.dist-info/METADATA
sudeep-0.1.0.dist-info/WHEEL
sudeep-0.1.0.dist-info/top_level.txt
sudeep-0.1.0.dist-info/RECORD
