Metadata-Version: 2.1
Name: sudeep
Version: 0.1.0
Summary: About Sudeep
Home-page: https://github.com/amalrajan/sudeep
Author: Amal Rajan
Author-email: amalrajan@outlook.com
License: MIT
